[{"title":"Teste <i class=\"fas fa-exclamation-triangle\"><\/i>","task_id":"11","prioridade":"Urgente","titulo_tarefa":"Teste","ptc":"3","data_vencimento":"2023-11-17 18:08:00","data_criada":"2023-11-16 16:09:11","criado_por":"admin","descricao":"tst"},{"title":"Criar a l\u00f3gica de gear LOGS no backend","task_id":"19","prioridade":"Normal","titulo_tarefa":"Criar a l\u00f3gica de gear LOGS no backend","ptc":"99988","data_vencimento":"2023-11-17 15:00:00","data_criada":"2023-11-17 09:07:55","criado_por":"admin","descricao":"Tarefa criada para teste"},{"title":"TESTE EMAIL  <i class=\"fas fa-exclamation-triangle\"><\/i>","task_id":"25","prioridade":"Urgente","titulo_tarefa":"TESTE EMAIL ","ptc":"9999","data_vencimento":"2023-11-29 16:30:00","data_criada":"2023-11-21 14:27:23","criado_por":"admin","descricao":"Tarefa criada para teste"},{"title":"teste","task_id":"31","prioridade":"Normal","titulo_tarefa":"teste","ptc":"23233","data_vencimento":"2023-11-23 10:00:00","data_criada":"2023-11-22 08:32:07","criado_por":"admin","descricao":"Tarefa criada para teste"}]